wild_devs_api/__init__.py
wild_devs_api/__version__.py
wild_devs_api/api.py
wild_devs_api/restclient.py
wild_devs_api/endpoints/__init__.py
wild_devs_api/endpoints/ai.py
wild_devs_api/endpoints/conversion.py
wild_devs_api/endpoints/games.py
wild_devs_api/endpoints/mockup.py
wild_devs_api/endpoints/moviefinder.py
wild_devs_api/endpoints/nettools.py
wild_devs_api/endpoints/opendata.py
wild_devs_api/endpoints/random.py
wild_devs_api/endpoints/urlshortener.py
wild_devs_api/endpoints/utility.py
wild_devs_api/endpoints/validation.py
wild_devs_api/errors/__init__.py
wild_devs_api/errors/errors.py
wild_devs_api/models/__init__.py
wild_devs_api/models/response.py
wild_devs_api/models/response_headers.py
wilddevs_api-0.5.1.dist-info/LICENSE
wilddevs_api-0.5.1.dist-info/METADATA
wilddevs_api-0.5.1.dist-info/WHEEL
wilddevs_api-0.5.1.dist-info/top_level.txt
wilddevs_api-0.5.1.dist-info/RECORD
